Metadata-Version: 2.4
Name: phytrace
Version: 0.1.1
Summary: A Python library that adds provenance tracking, invariant checking, and evidence generation to scientific simulations
Author: phytrace contributors
License: MIT License
Project-URL: Homepage, https://github.com/yourusername/phytrace
Project-URL: Documentation, https://phytrace.readthedocs.io
Project-URL: Repository, https://github.com/yourusername/phytrace
Project-URL: Issues, https://github.com/yourusername/phytrace/issues
Keywords: simulation,provenance,reproducibility,scientific-computing,ode,invariants
Classifier: Development Status :: 3 - Alpha
Classifier: Intended Audience :: Science/Research
Classifier: License :: OSI Approved :: MIT License
Classifier: Programming Language :: Python :: 3
Classifier: Programming Language :: Python :: 3.9
Classifier: Programming Language :: Python :: 3.10
Classifier: Programming Language :: Python :: 3.11
Classifier: Programming Language :: Python :: 3.12
Classifier: Topic :: Scientific/Engineering
Requires-Python: >=3.9
License-File: LICENSE
Requires-Dist: numpy>=1.24
Requires-Dist: scipy>=1.11
Requires-Dist: matplotlib>=3.7
Provides-Extra: full
Requires-Dist: pandas; extra == "full"
Requires-Dist: h5py; extra == "full"
Requires-Dist: gitpython; extra == "full"
Provides-Extra: dev
Requires-Dist: pytest>=7.0; extra == "dev"
Requires-Dist: pytest-cov>=4.0; extra == "dev"
Requires-Dist: black>=23.0; extra == "dev"
Requires-Dist: mypy>=1.0; extra == "dev"
Dynamic: license-file
